grimbert/datas.py
grimbert/model.py
grimbert/predict.py
grimbert/py.typed
grimbert/run_train.py
grimbert/score.py
grimbert/train.py
grimbert/utils.py
grimbert-0.1.5.dist-info/METADATA
grimbert-0.1.5.dist-info/WHEEL
grimbert-0.1.5.dist-info/licenses/LICENSE
grimbert-0.1.5.dist-info/RECORD
