Metadata-Version: 2.4
Name: grimbert
Version: 0.1.5
Author: Arthur Amalvy
License: GPL-3.0-only
License-File: LICENSE
Requires-Python: <3.13,>=3.9
Requires-Dist: accelerate>=1.10.1
Requires-Dist: more-itertools>=10.7
Requires-Dist: pandas>=2.0
Requires-Dist: rich>=13.5
Requires-Dist: sacred>=0.8
Requires-Dist: sacremoses>=0.1.1
Requires-Dist: scikit-learn>=1.6.0
Requires-Dist: torch>=2.7.0
Requires-Dist: transformers>=4.56.1
